fem/__init__.py
fem/basis_functions.py
fem/boundary_conditions.py
fem/fem_solver.py
fem/ode.py
fem/printer.py
pyFEMSolver-0.0.1.dist-info/METADATA
pyFEMSolver-0.0.1.dist-info/WHEEL
pyFEMSolver-0.0.1.dist-info/top_level.txt
pyFEMSolver-0.0.1.dist-info/RECORD
