Metadata-Version: 2.1
Name: pyFEMSolver
Version: 0.0.1
Summary: The finite element method to solve differential equations
Author-email: AvanishMeedimale <avanish.meedimale@gmail.com>, sap6 <sapcxi@gmail.com>
Classifier: Programming Language :: Python :: 3
Classifier: License :: OSI Approved :: MIT License
Classifier: Operating System :: Microsoft :: Windows
Requires-Python: >=3.10.9
